timv.py
timv-0.0.1.dist-info/LICENSE.txt
timv-0.0.1.dist-info/METADATA
timv-0.0.1.dist-info/WHEEL
timv-0.0.1.dist-info/top_level.txt
timv-0.0.1.dist-info/RECORD
