Metadata-Version: 2.1
Name: timv
Version: 0.0.1
Summary: Say hello!
Home-page: https://github.com/valteresj2/Tree-Imput-Missing-Values
Author: Valter Eduardo da Silva Junior
Author-email: valteresj2@gmail.com
License: UNKNOWN
Platform: UNKNOWN
License-File: LICENSE.txt
Requires-Dist: numpy (>=1.19.5)
Requires-Dist: pandas (>=1.1.5)
Requires-Dist: info-gain (>=1.0.1)
